acrosort_tex/__init__.py
acrosort_tex/sorter.py
LICENSE
acrosort_tex-0.1.2.dist-info/entry_points.txt
acrosort_tex-0.1.2.dist-info/LICENSE
acrosort_tex-0.1.2.dist-info/WHEEL
acrosort_tex-0.1.2.dist-info/METADATA
acrosort_tex-0.1.2.dist-info/RECORD
