Metadata-Version: 2.1
Name: acrosort-tex
Version: 0.1.2
Summary: 
Home-page: https://github.com/baniasbaabe/acrosort-tex/tree/main
License: MIT
Keywords: latex,acronyms,sorting
Author: baniasbaabe
Author-email: banias@hotmail.de
Requires-Python: >=3.8,<4.0
Classifier: Environment :: Console
Classifier: License :: OSI Approved :: MIT License
Classifier: Operating System :: OS Independent
Classifier: Programming Language :: Python :: 3
Classifier: Programming Language :: Python :: 3.10
Classifier: Programming Language :: Python :: 3.8
Classifier: Programming Language :: Python :: 3.9
Classifier: Topic :: Software Development :: Libraries :: Python Modules
Classifier: Topic :: Text Processing :: Markup :: LaTeX
Requires-Dist: rich (>=13.3.5,<14.0.0)
Project-URL: Repository, https://github.com/baniasbaabe/acrosort-tex/tree/main
